Workbook

Sheet Affordability
F6: MY INCOME
F7: MONTHLY SALARY
F8: TOTAL ANNUAL SALARY | G8: =G7*12 -> 0
F10: COST OF BUYING THE CAR | L10: To Support Your Money Purse Channel Use the Links Below
F11: ON ROAD CAR PRICE | L11: Compare Term Plan Here | M11: https://tinyurl.com/44tp7uor
F12: DOWN PAYMENT % | L12: Compare Health Insurance Here | M12: https://tinyurl.com/pgc9dcxc
F13: DOWN PAYMENT VALUE | G13: =G11*G12 -> 0
F14: LOAN AMOUNT | G14: =G11-G13 -> 0 | L14: Choose the Credit Card Which Suits Your Requirement
F15: LOAN TENURE YEARS | L15: State Bank Of India | M15: https://wee.bnking.in/c/NzRkOGY4
F16: LOAN RATE | L16: Axis Bank | M16: https://wee.bnking.in/c/M2M3MjM1
F17: EMI | G17: =-PMT(G16/12,G15*12,G14,0) -> #NUM! | L17: IDFC First Bank | M17: https://wee.bnking.in/ZTFkZTc1
F18: TOTAL VALUE OF EMIs PER ANNUM | G18: =G17*12 -> #NUM!
F19: PERCENTAGE OF MY INCOME | G19: =G18/G8 -> #NUM!
F21: OPERATIONAL COST
F22: AVG COMMUTATION PER MONTH
F23: MILEAGE
F24: FUEL COST PER LITRE
F25: COST OF COMMUTATION PER MONTH | G25: =(G22/G23)*G24 -> #DIV/0!
F26: TOTAL COST OF COMMUTATION PER YEAR | G26: =G25*12 -> #DIV/0!
F27: SERVICE COST
F29: TOTAL EXPENSE TO MAINTAIN A CAR | G29: =G18+G26+G27 -> #NUM!
F30: PERCENTAGE OF MY INCOME | G30: =G29/G8 -> #NUM!

Sheet Owing Cost
D7: FIXED COST OF OWNING THE CAR | Q7: BUY THE CAR AT FREE OF COST
D8: ON ROAD PRICE OF THE VEHICLE | E8: =Affordability!G11 -> 0 | Q8: EMI | R8: =Affordability!G17 -> #NUM! | V8: TENURE | W8: MULTIPLE
D9: INTEREST PAID | E9: =(Affordability!G17*Affordability!G15*12)-Affordability!G14 -> #NUM! | Q9: INVESTMENT | R9: =R8 -> #NUM! | V9: 4 | W9: 1.63
D10: TOTAL COST OF THE VEHICLE | E10: =E8+E9 -> #NUM! | I10: To Support Your Money Purse Channel Use the Links Below | Q10: TENURE | R10: =Affordability!G15 -> 0 | V10: 5 | W10: 1.5
I11: Compare Term Plan Here | J11: https://tinyurl.com/44tp7uor | Q11: EXPECTED RETURN | R11: 0.12 | V11: 6 | W11: 1.38
D12: OPERATIONAL COST OF THE CAR | I12: Compare Health Insurance Here | J12: https://tinyurl.com/pgc9dcxc | Q12: VALUE AT THE END OF TENURE | R12: =FV(NOMINAL(R11,12)/12,R10*12,-R9,0) -> #NUM! | V12: 7 | W12: 1.27
D13: COMMUTATION EXPENSES PER YEAR | E13: =Affordability!G26 -> #DIV/0! | Q13: TIME LEFT POST TENURE | R13: =E16-R10 -> 10
D14: SERVICE COST PER YEAR | E14: =Affordability!G27 -> 0 | I14: Choose the Credit Card Which Suits Your Requirement | Q14: VALUE OF INVESTMENT BY 10 YEARS | R14: =FV(R11,R13,0,-R12) -> #NUM!
D15: INSURANCE COST PER YEAR | E15: =E8*0.03 -> 0 | I15: State Bank Of India | J15: https://wee.bnking.in/c/NzRkOGY4 | Q15: TOTAL EXPENSE ON OWNING THE CAR | R15: =E22 -> #DIV/0!
D16: TENURE | E16: 10 | I16: Axis Bank | J16: https://wee.bnking.in/c/M2M3MjM1 | Q16: GAINS OVER AND ABOVE | R16: =R14-R15 -> #NUM!
D17: TOTAL OPERATIONAL COST OF THE CAR | E17: =(E13+E14)*E16+(E15*(E16-1)) -> #DIV/0! | I17: IDFC First Bank | J17: https://wee.bnking.in/ZTFkZTc1
D19: TOTAL COST OF OWNING A CAR FOR 10 YEARS | E19: =E17+E10 -> #DIV/0!
D20: CAR VALUE AFTER 10 YEARS | E20: =E8*0.3 -> 0
D22: TOTAL EXPENSE ON OWNING A CAR FOR 10 YEARS | E22: =E19-E20 -> #DIV/0!
