Workbook

Sheet F S NUMBER
C2: NAME
C3: AGE
C4: CURRENT MONTHLY EXPENSE
C5: FINANCIAL FREEDOM NUMBER | D5: ='THE ACTUAL FSN'!F20 -> 0 | K5: Inflation | L5: Expected Return P.R | M5: Real Rate
K6: 0.06 | L6: 0.08 | M6: =((1+L6)/(1+K6))-1 -> 0.018867925
I7: Age | J7: Initial Corpus | K7: Return on Investment | L7: Annual Expense | M7: End Value
I8: ='THE ACTUAL FSN'!$F$8+'THE ACTUAL FSN'!$F$13 -> 0 | J8: =$D$5 -> 0 | K8: =(J8)*$L$6 -> 0 | L8: ='THE ACTUAL FSN'!F14*12*(1+$K$6) -> 0 | M8: =J8+K8-L8 -> 0
I9: =IF(I8<'THE ACTUAL FSN'!$F$10,I8+1, "NA") -> 1 | J9: =IF(I9= "NA",0,M8) -> 0 | K9: =(J9)*$L$6 -> 0 | L9: =IF(M8<=0,0,L8*(1+$K$6)) -> 0 | M9: =J9+K9-L9 -> 0
I10: =IF(I9<'THE ACTUAL FSN'!$F$10,I9+1, "NA") -> 2 | J10: =IF(I10= "NA",0,M9) -> 0 | K10: =(J10)*$L$6 -> 0 | L10: =IF(M9<=0,0,L9*(1+$K$6)) -> 0 | M10: =J10+K10-L10 -> 0
I11: =IF(I10<'THE ACTUAL FSN'!$F$10,I10+1, "NA") -> 3 | J11: =IF(I11= "NA",0,M10) -> 0 | K11: =(J11)*$L$6 -> 0 | L11: =IF(M10<=0,0,L10*(1+$K$6)) -> 0 | M11: =J11+K11-L11 -> 0
I12: =IF(I11<'THE ACTUAL FSN'!$F$10,I11+1, "NA") -> 4 | J12: =IF(I12= "NA",0,M11) -> 0 | K12: =(J12)*$L$6 -> 0 | L12: =IF(M11<=0,0,L11*(1+$K$6)) -> 0 | M12: =J12+K12-L12 -> 0
I13: =IF(I12<'THE ACTUAL FSN'!$F$10,I12+1, "NA") -> 5 | J13: =IF(I13= "NA",0,M12) -> 0 | K13: =(J13)*$L$6 -> 0 | L13: =IF(M12<=0,0,L12*(1+$K$6)) -> 0 | M13: =J13+K13-L13 -> 0
I14: =IF(I13<'THE ACTUAL FSN'!$F$10,I13+1, "NA") -> 6 | J14: =IF(I14= "NA",0,M13) -> 0 | K14: =(J14)*$L$6 -> 0 | L14: =IF(M13<=0,0,L13*(1+$K$6)) -> 0 | M14: =J14+K14-L14 -> 0
I15: =IF(I14<'THE ACTUAL FSN'!$F$10,I14+1, "NA") -> 7 | J15: =IF(I15= "NA",0,M14) -> 0 | K15: =(J15)*$L$6 -> 0 | L15: =IF(M14<=0,0,L14*(1+$K$6)) -> 0 | M15: =J15+K15-L15 -> 0
I16: =IF(I15<'THE ACTUAL FSN'!$F$10,I15+1, "NA") -> 8 | J16: =IF(I16= "NA",0,M15) -> 0 | K16: =(J16)*$L$6 -> 0 | L16: =IF(M15<=0,0,L15*(1+$K$6)) -> 0 | M16: =J16+K16-L16 -> 0
I17: =IF(I16<'THE ACTUAL FSN'!$F$10,I16+1, "NA") -> 9 | J17: =IF(I17= "NA",0,M16) -> 0 | K17: =(J17)*$L$6 -> 0 | L17: =IF(M16<=0,0,L16*(1+$K$6)) -> 0 | M17: =J17+K17-L17 -> 0
I18: =IF(I17<'THE ACTUAL FSN'!$F$10,I17+1, "NA") -> 10 | J18: =IF(I18= "NA",0,M17) -> 0 | K18: =(J18)*$L$6 -> 0 | L18: =IF(M17<=0,0,L17*(1+$K$6)) -> 0 | M18: =J18+K18-L18 -> 0
I19: =IF(I18<'THE ACTUAL FSN'!$F$10,I18+1, "NA") -> 11 | J19: =IF(I19= "NA",0,M18) -> 0 | K19: =(J19)*$L$6 -> 0 | L19: =IF(M18<=0,0,L18*(1+$K$6)) -> 0 | M19: =J19+K19-L19 -> 0
I20: =IF(I19<'THE ACTUAL FSN'!$F$10,I19+1, "NA") -> 12 | J20: =IF(I20= "NA",0,M19) -> 0 | K20: =(J20)*$L$6 -> 0 | L20: =IF(M19<=0,0,L19*(1+$K$6)) -> 0 | M20: =J20+K20-L20 -> 0
... I107: =IF(I106<'THE ACTUAL FSN'!$F$10,I106+1, "NA") -> 99 | J107: =IF(I107= "NA",0,M106) -> 0 | K107: =(J107)*$L$6 -> 0 | L107: =IF(M106<=0,0,L106*(1+$K$6)) -> 0 | M107: =J107+K107-L107 -> 0

Sheet THE ACTUAL FSN
D4: RETIREMENT | K4: CHILD 1 FUTURE PLANNING | AB4: CHILD 2 FUTURE PLANNING | AS4: CHILD 3 FUTURE PLANNING | BJ4: HOUSE | BQ4: CAR | BX4: VACATION | CE4: STARTUP PLAN
D6: RETIREMENT OF MR & MRS | F6: ='F S NUMBER'!D2 -> 0 | K6: PLANNING FOR GRADUATION OF | P6: PLANNING FOR PG OF | Q6: =L6 -> 0 | U6: PLANNING FOR WEDDING OF | V6: =L6 -> 0 | AB6: PLANNING FOR EDUCATION OF | AG6: PLANNING FOR EDUCATION OF | AH6: =AC6 -> 0 | AL6: PLANNING FOR WEDDING OF | AM6: =AC6 -> 0 | AS6: PLANNING FOR EDUCATION OF | AX6: PLANNING FOR EDUCATION OF | AY6: =AT6 -> 0 | BC6: PLANNING FOR WEDDING OF | BD6: =AT6 -> 0 | BJ6: DREAM | BQ6: DREAM | BX6: TRIP TO | CE6: THE STARTUP
D8: PRESENT AGE | F8: ='F S NUMBER'!D3 -> 0 | K8: PRESENT CHILD AGE | N8: YEARS | P8: PRESENT CHILD AGE | R8: =M8 -> 0 | S8: YEARS | U8: PRESENT CHILD AGE | W8: =M8 -> 0 | X8: YEARS | AB8: PRESENT CHILD AGE | AE8: YEARS | AG8: PRESENT CHILD AGE | AI8: =AD8 -> 0 | AJ8: YEARS | AL8: PRESENT CHILD AGE | AN8: =AD8 -> 0 | AO8: YEARS | AS8: PRESENT CHILD AGE | AV8: YEARS | AX8: PRESENT CHILD AGE | AZ8: =AU8 -> 0 | BA8: YEARS | BC8: PRESENT CHILD AGE | BE8: =AU8 -> 0 | BF8: YEARS | BJ8: PRESENT CHILD AGE | BM8: YEARS | BQ8: PRESENT CHILD AGE | BT8: YEARS | BX8: PRESENT CHILD AGE | CA8: YEARS | CE8: PRESENT CHILD AGE | CH8: YEARS
D9: WISH TO DELAY RETIREMENT TILL AGE | F9: =F8 -> 0 | K9: CURRENT COST OF THE EDUCATION | P9: CURRENT COST OF THE EDUCATION | U9: CURRENT COST OF WEDDING | AB9: CURRENT COST OF THE EDUCATION | AG9: CURRENT COST OF THE EDUCATION | AL9: CURRENT COST OF THE WEDDING | AS9: CURRENT COST OF THE EDUCATION | AX9: CURRENT COST OF THE EDUCATION | BC9: CURRENT COST OF THE WEDDING | BJ9: CURRENT COST OF YOUR DREAM HOUSE | BQ9: CURRENT COST OF YOUR DREAM CAR | BX9: CURRENT COST OF THE TRIP | CE9: CURRENT COST OF THE SET UP
D10: LIFE EXPECTANCY | F10: 100 | BX10: EXPECTED INFLATION OF THE TOTAL TOUR
D11: PRESENT EXPENSES | F11: ='F S NUMBER'!D4 -> 0 | K11: EXPECTED INFLATION | P11: EXPECTED INFLATION | R11: =M11 -> 0 | U11: EXPECTED INFLATION | AB11: EXPECTED INFLATION | AG11: EXPECTED INFLATION | AI11: =AD11 -> 0 | AL11: EXPECTED INFLATION | AS11: EXPECTED INFLATION | AX11: EXPECTED INFLATION | AZ11: =AU11 -> 0 | BC11: EXPECTED INFLATION | BJ11: EXPECTED INFLATION OF PROPERTY | BQ11: EXPECTED INFLATION OF VEHICLE | BX11: HOW OFTEN YOU WISH TO TRAVEL | CA11: YEARS | CE11: EXPECTED INFLATION TO SET UP
D12: EXPECTED INFLATION | F12: 0.06 | K12: AGE OF THE CHILD @ THE GOAL | N12: YEARS | P12: AGE OF THE CHILD @ THE GOAL | S12: YEARS | U12: AGE OF THE CHILD @ THE GOAL | X12: YEARS | AB12: AGE OF THE CHILD @ THE GOAL | AE12: YEARS | AG12: AGE OF THE CHILD @ THE GOAL | AJ12: YEARS | AL12: AGE OF THE CHILD @ THE GOAL | AO12: YEARS | AS12: AGE OF THE CHILD @ THE GOAL | AV12: YEARS | AX12: AGE OF THE CHILD @ THE GOAL | BA12: YEARS | BC12: AGE OF THE CHILD @ THE GOAL | BF12: YEARS | BJ12: TIME LEFT TO BUY THE HOUSE | BM12: YEARS | BQ12: TIME LEFT TO BUY THE CAR | BT12: YEARS | BX12: TILL WHAT AGE YOU WISH TO TRAVEL | CA12: YEARS | CE12: TIME LEFT TO SET UP THE BUSINESS | CH12: YEARS
D13: YEARS LEFT TO RETIRE | F13: =F9-F8 -> 0 | K13: CORPUS REQUIRED TO MEET THE GOAL | M13: =FV(M11,M12-M8,0,-M9) -> 0 | P13: CORPUS REQUIRED TO MEET THE GOAL | R13: =FV(R11,R12-R8,0,-R9) -> 0 | U13: CORPUS REQUIRED TO MEET THE GOAL | W13: =FV(W11,W12-W8,0,-W9) -> 0 | AB13: CORPUS REQUIRED TO MEET THE GOAL | AD13: =FV(AD11,AD12-AD8,0,-AD9) -> 0 | AG13: CORPUS REQUIRED TO MEET THE GOAL | AI13: =FV(AI11,AI12-AI8,0,-AI9) -> 0 | AL13: CORPUS REQUIRED TO MEET THE GOAL | AN13: =FV(AN11,AN12-AN8,0,-AN9) -> 0 | AS13: CORPUS REQUIRED TO MEET THE GOAL | AU13: =FV(AU11,AU12-AU8,0,-AU9) -> 0 | AX13: CORPUS REQUIRED TO MEET THE GOAL | AZ13: =FV(AZ11,AZ12-AZ8,0,-AZ9) -> 0 | BC13: CORPUS REQUIRED TO MEET THE GOAL | BE13: =FV(BE11,BE12-BE8,0,-BE9) -> 0 | BJ13: CORPUS REQUIRED TO MEET THE GOAL | BL13: =FV(BL11,BL12-BL8,0,-BL9) -> 0 | BQ13: CORPUS REQUIRED TO MEET THE GOAL | BS13: =FV(BS11,BS12-BS8,0,-BS9) -> 0 | BX13: INFLATED COST OF THE TRIP | BZ13: =FV(BZ10,BZ11,0,-BZ9) -> 0 | CE13: CORPUS REQUIRED TO MEET THE GOAL | CG13: =FV(CG11,CG12-CG8,0,-CG9) -> 0
D14: EXPENSES AT RETIREMENT AGE | F14: =FV(F12,F13,0,-F11,0) -> 0
BJ15: EXPECTED RETURN ON INVESTMENT | BQ15: EXPECTED RETURN ON INVESTMENT | BX15: EXPECTED RETURN ON INVESTMENT | CE15: EXPECTED RETURN ON INVESTMENT
D16: MONTHLY EXPENSE AT RETIREMENT | F16: =F14 -> 0
D17: RETURNS EXPECTED POST RETIREMENT | F17: 0.08
D18: INFLATION POST RETIREMENT | F18: 0.06
D19: INFLATION ADJUSTED RETURN | F19: =((1+F17)/(1+F18))-1 -> 0.018867925
D20: CORPUS REQUIRED AT RETIREMENT | F20: =PV(F19,F10-F9,-F16*12,0) -> 0
D21: EXPECTED RETURN ON INVESTMENT | F21: 0.12 | K21: EXPECTED RETURN ON INVESTMENT | P21: EXPECTED RETURN ON INVESTMENT | U21: EXPECTED RETURN ON INVESTMENT | AB21: EXPECTED RETURN ON INVESTMENT | AG21: EXPECTED RETURN ON INVESTMENT | AL21: EXPECTED RETURN ON INVESTMENT | AS21: EXPECTED RETURN ON INVESTMENT | AX21: EXPECTED RETURN ON INVESTMENT | BC21: EXPECTED RETURN ON INVESTMENT | BJ21: EXPECTED RETURN ON INVESTMENT | BQ21: EXPECTED RETURN ON INVESTMENT | BX21: EXPECTED RETURN ON INVESTMENT | CE21: EXPECTED RETURN ON INVESTMENT | CG21: 0.12
D22: MONTHLY INVESTMENT REQUIRED | F22: =-PMT(NOMINAL(F21,12)/12,(F9-F8)*12,0,F20) -> #NUM! | K22: MONTHLY INVESTMENT REQUIRED | M22: =-PMT(NOMINAL(M21,12)/12,(M12-M8)*12,0,M13) -> #NUM! | P22: MONTHLY INVESTMENT REQUIRED | R22: =-PMT(NOMINAL(R21,12)/12,(R12-R8)*12,0,R13) -> #NUM! | U22: MONTHLY INVESTMENT REQUIRED | W22: =-PMT(NOMINAL(W21,12)/12,(W12-W8)*12,0,W13) -> #NUM! | AB22: MONTHLY INVESTMENT REQUIRED | AD22: =-PMT(NOMINAL(AD21,12)/12,(AD12-AD8)*12,0,AD13) -> #NUM! | AG22: MONTHLY INVESTMENT REQUIRED | AI22: =-PMT(NOMINAL(AI21,12)/12,(AI12-AI8)*12,0,AI13) -> #NUM! | AL22: MONTHLY INVESTMENT REQUIRED | AN22: =-PMT(NOMINAL(AN21,12)/12,(AN12-AN8)*12,0,AN13) -> #NUM! | AS22: MONTHLY INVESTMENT REQUIRED | AU22: =-PMT(NOMINAL(AU21,12)/12,(AU12-AU8)*12,0,AU13) -> #NUM! | AX22: MONTHLY INVESTMENT REQUIRED | AZ22: =-PMT(NOMINAL(AZ21,12)/12,(AZ12-AZ8)*12,0,AZ13) -> #NUM! | BC22: MONTHLY INVESTMENT REQUIRED | BE22: =-PMT(NOMINAL(BE21,12)/12,(BE12-BE8)*12,0,BE13) -> #NUM! | BJ22: MONTHLY INVESTMENT REQUIRED | BL22: =-PMT(NOMINAL(BL21,12)/12,BL12*12,0,BL13) -> #NUM! | BQ22: MONTHLY INVESTMENT REQUIRED | BS22: =-PMT(NOMINAL(BS21,12)/12,BS12*12,0,BS13) -> #NUM! | BX22: MONTHLY INVESTMENT REQUIRED | BZ22: =CAL!G5 -> #NUM! | CE22: MONTHLY INVESTMENT REQUIRED | CG22: =-PMT(NOMINAL(CG21,12)/12,CG12*12,0,CG13) -> #NUM!
D23: LUMPSUM INVESTMENT REQUIRED | F23: =-PV(F21,F9-F8,0,F20,0) -> 0 | K23: LUMPSUM INVESTMENT REQUIRED | M23: =-PV(M21,M12-M8,0,M13) -> 0 | P23: LUMPSUM INVESTMENT REQUIRED | R23: =-PV(R21,R12-R8,0,R13) -> 0 | U23: LUMPSUM INVESTMENT REQUIRED | W23: =-PV(W21,W12-W8,0,W13) -> 0 | AB23: LUMPSUM INVESTMENT REQUIRED | AD23: =-PV(AD21,AD12-AD8,0,AD13) -> 0 | AG23: LUMPSUM INVESTMENT REQUIRED | AI23: =-PV(AI21,AI12-AI8,0,AI13) -> 0 | AL23: LUMPSUM INVESTMENT REQUIRED | AN23: =-PV(AN21,AN12-AN8,0,AN13) -> 0 | AS23: LUMPSUM INVESTMENT REQUIRED | AU23: =-PV(AU21,AU12-AU8,0,AU13) -> 0 | AX23: LUMPSUM INVESTMENT REQUIRED | AZ23: =-PV(AZ21,AZ12-AZ8,0,AZ13) -> 0 | BC23: LUMPSUM INVESTMENT REQUIRED | BE23: =-PV(BE21,BE12-BE8,0,BE13) -> 0 | BJ23: LUMPSUM INVESTMENT REQUIRED | BL23: =-PV(BL21,BL12,0,BL13) -> 0 | BQ23: LUMPSUM INVESTMENT REQUIRED | BS23: =-PV(BS21,BS12,0,BS13) -> 0 | BX23: LUMPSUM INVESTMENT REQUIRED | BZ23: =CAL!E5 -> 0 | CE23: LUMPSUM INVESTMENT REQUIRED | CG23: =-PV(CG21,CG12,0,CG13) -> 0
M28: COMPARE TERM INSURANCE & HEALTH INSURANCE HERE
D29: FINANCIAL SAFETY NUMBER | F29: =F20+M13+R13+W13+AD13+AI13+AN13+AU13+AZ13+BE13+BL13+BS13+BZ23+CG13 -> 0 | M29: TERM INSURANCE | P29: https://bit.ly/46hsSJA
M30: HEALTH INSURANCE | P30: https://tinyurl.com/pgc9dcxc
D32: LUMPSUM INVESTMENT REQUIRED | F32: =F23+M23+R23+W23+AD23+AI23+AN23+AU23+AZ23+BE23+BL23+BS23+BZ23+CG23 -> 0

Sheet CAL
C1: ='THE ACTUAL FSN'!BZ12 -> 0 | D1: ='THE ACTUAL FSN'!BZ11 -> 0
B2: ='F S NUMBER'!D3 -> 0 | C2: ='THE ACTUAL FSN'!BZ10 -> 0 | D2: ='THE ACTUAL FSN'!BZ9 -> 0 | E2: {='THE ACTUAL FSN'!BZ21:CA21} -> 0 | F2: 0
B3: once in a year
B4: year | C4: Money Required | D4: Amount Required
B5: =IF(B2+$D$1<=$C$1,B2+$D$1,0) -> 0 | C5: =IF(B5="NA",0,-FV($C$2,B5-B2,0,D2)) -> 0 | D5: =-PV($E$2,B5-B2,0,C5) -> 0 | E5: =SUM(D5:D55) -> 0 | F5: =-PMT(NOMINAL(E2,12)/12,(B5-$B$2)*12,0,C5) -> #NUM! | G5: =SUM(F5:F55) -> #NUM!
B6: =IF(B5>0,IF(B5+$D$1<=$C$1,B5+$D$1,0),0) -> 0 | C6: =IF(B6=0,0,-FV($C$2,B6-B5,0,C5)) -> 0 | D6: =-PV($E$2,B6-$B$2,0,C6) -> 0 | F6: =-PMT(NOMINAL($E$2,12)/12,(B6-$B$2)*12,0,C6) -> #NUM!
B7: =IF(B6>0,IF(B6+$D$1<=$C$1,B6+$D$1,0),0) -> 0 | C7: =IF(B7=0,0,-FV($C$2,B7-B6,0,C6)) -> 0 | D7: =-PV($E$2,B7-$B$2,0,C7) -> 0 | F7: =-PMT(NOMINAL($E$2,12)/12,(B7-$B$2)*12,0,C7) -> #NUM!
B8: =IF(B7>0,IF(B7+$D$1<=$C$1,B7+$D$1,0),0) -> 0 | C8: =IF(B8=0,0,-FV($C$2,B8-B7,0,C7)) -> 0 | D8: =-PV($E$2,B8-$B$2,0,C8) -> 0 | F8: =-PMT(NOMINAL($E$2,12)/12,(B8-$B$2)*12,0,C8) -> #NUM!
B9: =IF(B8>0,IF(B8+$D$1<=$C$1,B8+$D$1,0),0) -> 0 | C9: =IF(B9=0,0,-FV($C$2,B9-B8,0,C8)) -> 0 | D9: =-PV($E$2,B9-$B$2,0,C9) -> 0 | F9: =-PMT(NOMINAL($E$2,12)/12,(B9-$B$2)*12,0,C9) -> #NUM!
B10: =IF(B9>0,IF(B9+$D$1<=$C$1,B9+$D$1,0),0) -> 0 | C10: =IF(B10=0,0,-FV($C$2,B10-B9,0,C9)) -> 0 | D10: =-PV($E$2,B10-$B$2,0,C10) -> 0 | F10: =-PMT(NOMINAL($E$2,12)/12,(B10-$B$2)*12,0,C10) -> #NUM!
B11: =IF(B10>0,IF(B10+$D$1<=$C$1,B10+$D$1,0),0) -> 0 | C11: =IF(B11=0,0,-FV($C$2,B11-B10,0,C10)) -> 0 | D11: =-PV($E$2,B11-$B$2,0,C11) -> 0 | F11: =-PMT(NOMINAL($E$2,12)/12,(B11-$B$2)*12,0,C11) -> #NUM!
B12: =IF(B11>0,IF(B11+$D$1<=$C$1,B11+$D$1,0),0) -> 0 | C12: =IF(B12=0,0,-FV($C$2,B12-B11,0,C11)) -> 0 | D12: =-PV($E$2,B12-$B$2,0,C12) -> 0 | F12: =-PMT(NOMINAL($E$2,12)/12,(B12-$B$2)*12,0,C12) -> #NUM!
B13: =IF(B12>0,IF(B12+$D$1<=$C$1,B12+$D$1,0),0) -> 0 | C13: =IF(B13=0,0,-FV($C$2,B13-B12,0,C12)) -> 0 | D13: =-PV($E$2,B13-$B$2,0,C13) -> 0 | F13: =-PMT(NOMINAL($E$2,12)/12,(B13-$B$2)*12,0,C13) -> #NUM!
B14: =IF(B13>0,IF(B13+$D$1<=$C$1,B13+$D$1,0),0) -> 0 | C14: =IF(B14=0,0,-FV($C$2,B14-B13,0,C13)) -> 0 | D14: =-PV($E$2,B14-$B$2,0,C14) -> 0 | F14: =-PMT(NOMINAL($E$2,12)/12,(B14-$B$2)*12,0,C14) -> #NUM!
B15: =IF(B14>0,IF(B14+$D$1<=$C$1,B14+$D$1,0),0) -> 0 | C15: =IF(B15=0,0,-FV($C$2,B15-B14,0,C14)) -> 0 | D15: =-PV($E$2,B15-$B$2,0,C15) -> 0 | F15: =-PMT(NOMINAL($E$2,12)/12,(B15-$B$2)*12,0,C15) -> #NUM!
B16: =IF(B15>0,IF(B15+$D$1<=$C$1,B15+$D$1,0),0) -> 0 | C16: =IF(B16=0,0,-FV($C$2,B16-B15,0,C15)) -> 0 | D16: =-PV($E$2,B16-$B$2,0,C16) -> 0 | F16: =-PMT(NOMINAL($E$2,12)/12,(B16-$B$2)*12,0,C16) -> #NUM!
B17: =IF(B16>0,IF(B16+$D$1<=$C$1,B16+$D$1,0),0) -> 0 | C17: =IF(B17=0,0,-FV($C$2,B17-B16,0,C16)) -> 0 | D17: =-PV($E$2,B17-$B$2,0,C17) -> 0 | F17: =-PMT(NOMINAL($E$2,12)/12,(B17-$B$2)*12,0,C17) -> #NUM!
... B55: =IF(B54>0,IF(B54+$D$1<=$C$1,B54+$D$1,0),0) -> 0 | C55: =IF(B55=0,0,-FV($C$2,B55-B54,0,C54)) -> 0 | D55: =-PV($E$2,B55-$B$2,0,C55) -> 0 | F55: =-PMT(NOMINAL($E$2,12)/12,(B55-$B$2)*12,0,C55) -> #NUM!
