Workbook

Sheet Funds & Performance
A2: SCHEME - E Tier-I | B2: Pension Fund | C2: Inception Date | D2: AUM (Rs Crs) | E2: Subscribers | F2: NAV | G2: Returns 1 Year | H2: Returns 3 Years | I2: Returns 5 Years | J2: Returns 7 Years | K2: Returns 10 Years | L2: Returns Inception
B3: Aditya Birla Sun Life Pension Fund Management Limited | C3: 42864 | D3: 1983.3273 | E3: 122208 | F3: 28.9748 | G3: -0.016910278 | H3: 0.15219554 | I3: 0.18311119 | J3: 0.13224127 | K3: NA | L3: 0.13553488
B4: Axis Pension Fund Management Limited | C4: 44855 | D4: 4812.391 | E4: 402817 | F4: 14.8743 | G4: -0.019699206 | H4: NA | I4: NA | J4: NA | K4: NA | L4: 0.14591792
B5: HDFC Pension Fund Management Ltd. | C5: 41487 | D5: 65132.281 | E5: 2598153 | F5: 54.8858 | G5: 0.0017338677 | H5: 0.15715613 | I5: 0.19365162 | J5: 0.14193168 | K5: 0.14105568 | L5: 0.15053286
B6: ICICI Pru. Pension Fund Mgmt Co. Ltd. | C6: 39951 | D6: 23275.761 | E6: 1029684 | F6: 74.3171 | G6: 0.00012650102 | H6: 0.1668518 | I6: 0.20242436 | J6: 0.14314454 | K6: 0.13807192 | L6: 0.1305125
B7: Kotak Mahindra Pension Fund Ltd. | C7: 39948 | D7: 3535.2078 | E7: 144524 | F7: 69.9431 | G7: 0.021073116 | H7: 0.1718492 | I7: 0.20361828 | J7: 0.14849466 | K7: 0.14122669 | L7: 0.12625889
B8: LIC Pension Fund Ltd. | C8: 41478 | D8: 7184.1214 | E8: 496748 | F8: 46.0762 | G8: 0.0036157542 | H8: 0.15349117 | I8: 0.19872342 | J8: 0.1348008 | K8: 0.12925522 | L8: 0.13378389
B9: SBI Pension Funds Pvt. Ltd | C9: 39948 | D9: 24583.633 | E9: 2189087 | F9: 57.5503 | G9: -0.022435456 | H9: 0.14019683 | I9: 0.17917023 | J9: 0.12652884 | K9: 0.12801081 | L9: 0.11291191
B10: Tata Pension Fund Management Pvt. Ltd. | C10: 44792 | D10: 2091.9293 | E10: 83286 | F10: 16.1867 | G10: 0.00014829186 | H10: 0.16937163 | I10: NA | J10: NA | K10: NA | L10: 0.16879899
B11: UTI Pension Fund Ltd. | C11: 39954 | D11: 4992.323 | E11: 203269 | F11: 74.0095 | G11: -0.010410747 | H11: 0.17275463 | I11: 0.20431771 | J11: 0.14197302 | K11: 0.13988474 | L11: 0.13029535
B12: DSP Pension Fund Managers Private Limited | C12: 45286 | D12: 2882.0005 | E12: 54242 | F12: 13.2935 | G12: 0.040066033 | H12: NA | I12: NA | J12: NA | K12: NA | L12: 0.17840025
B13: Benchmark Return as on 19-09-2025 | G13: -0.0052048016 | H13: 0.15503854 | I13: 0.19906204 | J13: 0.14436863 | K13: 0.14053007 | L13: =AVERAGE(L3:L11) -> 0.13717191
G14: =AVERAGE(G3:G12) -> -0.00026921239 | H14: =AVERAGE(H3,H5,H6,H7,H8,H9,H10,H11) -> 0.16048337 | I14: =AVERAGE(I3,I5,I6,I7,I8,I9,I11) -> 0.1950024 | J14: =AVERAGE(J3,J5,J6,J7,J8,J9,J11) -> 0.13844497 | K14: =AVERAGE(K5:K9,K11) -> 0.13625084 | L14: =AVERAGE(L3:L12) -> 0.14129474
A15: SCHEME - C Tier-I | B15: Pension Fund | C15: Inception Date | D15: AUM (Rs Crs) | E15: Subscribers | F15: NAV | G15: Returns 1 Year | H15: Returns 3 Years | I15: Returns 5 Years | J15: Returns 7 Years | K15: Returns 10 Years | L15: Returns Inception | S15: Returns 1 Year | T15: Returns 3 Years | U15: Returns 5 Years | V15: Returns 7 Years | W15: Returns 10 Years | X15: Returns Inception
B16: Aditya Birla Sun Life Pension Fund Management Limited | C16: 42864 | D16: 1267.7017 | E16: 122188 | F16: 19.6234 | G16: 0.082174783 | H16: 0.081592051 | I16: 0.068964659 | J16: 0.087504408 | K16: NA | L16: 0.083875939 | R16: E
B17: Axis Pension Fund Management Limited | C17: 44855 | D17: 3196.146 | E17: 398713 | F17: 12.5547 | G17: 0.083712419 | H17: NA | I17: NA | J17: NA | K17: NA | L17: 0.081172602
B18: HDFC Pension Fund Management Ltd. | C18: 41487 | D18: 27537.155 | E18: 2567923 | F18: 29.3053 | G18: 0.087806888 | H18: 0.083443213 | I18: 0.072509177 | J18: 0.090195404 | K18: 0.086177328 | L18: 0.092586897
B19: ICICI Pru. Pension Fund Mgmt Co. Ltd. | C19: 39951 | D19: 10875.184 | E19: 1012032 | F19: 44.0935 | G19: 0.085135391 | H19: 0.081927478 | I19: 0.069828927 | J19: 0.085912669 | K19: 0.084022404 | L19: 0.094988701
B20: Kotak Mahindra Pension Fund Ltd. | C20: 39948 | D20: 1368.2613 | E20: 139083 | F20: 42.2868 | G20: 0.084079565 | H20: 0.080843444 | I20: 0.068119819 | J20: 0.081630839 | K20: 0.08008865 | L20: 0.092142085
B21: LIC Pension Fund Ltd. | C21: 41478 | D21: 3956.9693 | E21: 497347 | F21: 28.4113 | G21: 0.082092025 | H21: 0.07923342 | I21: 0.06718337 | J21: 0.086536348 | K21: 0.082202817 | L21: 0.089611913
B22: SBI Pension Funds Pvt. Ltd | C22: 39948 | D22: 13122.989 | E22: 2182242 | F22: 44.28 | G22: 0.085829048 | H22: 0.081830121 | I22: 0.069447255 | J22: 0.086764597 | K22: 0.083675966 | L22: 0.095221319
B23: Tata Pension Fund Management Pvt. Ltd. | C23: 44792 | D23: 967.05973 | E23: 79418 | F23: 12.5712 | G23: 0.084247568 | H23: 0.078543791 | I23: NA | J23: NA | K23: NA | L23: 0.076923892
B24: UTI Pension Fund Ltd. | C24: 39954 | D24: 2083.8852 | E24: 194194 | F24: 39.1637 | G24: 0.085284916 | H24: 0.081521281 | I24: 0.067269516 | J24: 0.084403763 | K24: 0.08104907 | L24: 0.087123086
B25: DSP Pension Fund Managers Private Limited | C25: 45286 | D25: 1255.9573 | E25: 48061 | F25: 11.5635 | G25: 0.084420395 | H25: NA | I25: NA | J25: NA | K25: NA | L25: 0.08737291
B26: Benchmark Return as on 19-09-2025 | G26: 0.078317222 | H26: 0.077718333 | I26: 0.070755054 | J26: 0.089466249 | K26: 0.084478648
A28: SCHEME - G Tier-I | B28: Pension Fund | C28: Inception Date | D28: AUM (Rs Crs) | E28: Subscribers | F28: NAV | G28: Returns 1 Year | H28: Returns 3 Years | I28: Returns 5 Years | J28: Returns 7 Years | K28: Returns 10 Years | L28: Returns Inception
B29: Aditya Birla Sun Life Pension Fund Management Limited | C29: 42864 | D29: 2121.0671 | E29: 123707 | F29: 18.9075 | G29: 0.055777671 | H29: 0.083186727 | I29: 0.064915468 | J29: 0.089862316 | K29: NA | L29: 0.079073957
B30: Axis Pension Fund Management Limited | C30: 44855 | D30: 4500.4296 | E30: 399604 | F30: 12.5054 | G30: 0.04685368 | H30: NA | I30: NA | J30: NA | K30: NA | L30: 0.079714299
B31: HDFC Pension Fund Management Ltd. | C31: 41487 | D31: 44498.747 | E31: 2542755 | F31: 27.9143 | G31: 0.044532671 | H31: 0.079403964 | I31: 0.061326089 | J31: 0.088635095 | K31: 0.082086166 | L31: 0.088219953
B32: ICICI Pru. Pension Fund Mgmt Co. Ltd. | C32: 39951 | D32: 17509.134 | E32: 1003815 | F32: 37.4287 | G32: 0.051388651 | H32: 0.080008588 | I32: 0.061945054 | J32: 0.087118544 | K32: 0.081486537 | L32: 0.084069
B33: Kotak Mahindra Pension Fund Ltd. | C33: 39948 | D33: 2365.9341 | E33: 139488 | F33: 37.097 | G33: 0.040011438 | H33: 0.077115732 | I33: 0.061034198 | J33: 0.087550857 | K33: 0.08195896 | L33: 0.083435323
B34: LIC Pension Fund Ltd. | C34: 41478 | D34: 7660.4936 | E34: 531065 | F34: 30.3736 | G34: 0.054697483 | H34: 0.08159245 | I34: 0.063873768 | J34: 0.093158943 | K34: 0.087780823 | L34: 0.095609374
B35: SBI Pension Funds Pvt. Ltd | C35: 39948 | D35: 25172.23 | E35: 2199627 | F35: 40.7552 | G35: 0.05609959 | H35: 0.083335232 | I35: 0.06340495 | J35: 0.087806425 | K35: 0.083080782 | L35: 0.089681931
B36: Tata Pension Fund Management Pvt. Ltd. | C36: 44792 | D36: 1404.3585 | E36: 80491 | F36: 12.6261 | G36: 0.047200796 | H36: 0.08089962 | I36: NA | J36: NA | K36: NA | L36: 0.078444823
B37: UTI Pension Fund Ltd. | C37: 39954 | D37: 3703.0616 | E37: 196940 | F37: 36.4189 | G37: 0.055519327 | H37: 0.082783625 | I37: 0.063155845 | J37: 0.087819566 | K37: 0.080404157 | L37: 0.082300212
B38: DSP Pension Fund Managers Private Limited | C38: 45286 | D38: 1877.5266 | E38: 49342 | F38: 11.5638 | G38: 0.047796816 | H38: NA | I38: NA | J38: NA | K38: NA | L38: 0.087389176
B39: Benchmark Return as on 19-09-2025 | G39: 0.059792288 | H39: 0.08364877 | I39: 0.061594142 | J39: 0.086560489 | K39: 0.079223655
A41: SCHEME -A Tier-I | B41: Pension Fund | C41: Inception Date | D41: AUM (Rs Crs) | E41: Subscribers | F41: NAV | G41: Returns 1 Year | H41: Returns 3 Years | I41: Returns 5 Years | J41: Returns 7 Years | K41: Returns 10 Years | L41: Returns Inception
B42: Aditya Birla Sun Life Pension Fund Management Limited | C42: 42870 | D42: 6.8394177 | E42: 6328 | F42: 18.1978 | G42: 0.13830872 | H42: 0.086440741 | I42: 0.082828526 | J42: 0.075304344 | K42: NA | L42: 0.074304068
B43: Axis Pension Fund Management Limited | C43: 44855 | D43: 5.8774757 | E43: 13140 | F43: 12.5913 | G43: 0.11323991 | H43: NA | I43: NA | J43: NA | K43: NA | L43: 0.082252806
B44: HDFC Pension Fund Management Ltd. | C44: 42653 | D44: 475.50892 | E44: 235006 | F44: 22.4242 | G44: 0.16188167 | H44: 0.1043794 | I44: 0.10279677 | J44: 0.10388849 | K44: NA | L44: 0.0944483
B45: ICICI Pru. Pension Fund Mgmt Co. Ltd. | C45: 42695 | D45: 117.11671 | E45: 89192 | F45: 20.3292 | G45: 0.16967584 | H45: 0.098616603 | I45: 0.09570975 | J45: 0.090757777 | K45: NA | L45: 0.083635802
B46: Kotak Mahindra Pension Fund Ltd. | C46: 42657 | D46: 22.31666 | E46: 11486 | F46: 19.7801 | G46: 0.13981376 | H46: 0.091124307 | I46: 0.080820228 | J46: 0.0922021 | K46: NA | L46: 0.079310372
B47: LIC Pension Fund Ltd. | C47: 42656 | D47: 30.223681 | E47: 28091 | F47: 19.9768 | G47: 0.12004575 | H47: 0.086232984 | I47: 0.083496706 | J47: 0.085255988 | K47: NA | L47: 0.08048043
B48: SBI Pension Funds Pvt. Ltd | C48: 42656 | D48: 134.33981 | E48: 129007 | F48: 22.937 | G48: 0.15751651 | H48: 0.09750086 | I48: 0.096512575 | J48: 0.10645175 | K48: NA | L48: 0.097310958
B49: Tata Pension Fund Management Pvt. Ltd. | C49: 44792 | D49: 9.6512152 | E49: 6837 | F49: 14.1635 | G49: 0.1847146 | H49: 0.12198825 | I49: NA | J49: NA | K49: NA | L49: 0.11933328
B50: UTI Pension Fund Ltd. | C50: 42657 | D50: 28.176478 | E50: 15061 | F50: 20.8064 | G50: 0.25457659 | H50: 0.11981817 | I50: 0.10215722 | J50: 0.090285044 | K50: NA | L50: 0.0854367
B51: DSP Pension Fund Managers Private Limited | C51: 45287 | D51: 7.3494415 | E51: 2895 | F51: 11.1665 | G51: 0.067063557 | H51: NA | I51: NA | J51: NA | K51: NA | L51: 0.065794867
A53: SCHEME - E Tier-II | B53: Pension Fund | C53: Inception Date | D53: AUM (Rs Crs) | E53: Subscribers | F53: NAV | G53: Returns 1 Year | H53: Returns 3 Years | I53: Returns 5 Years | J53: Returns 7 Years | K53: Returns 10 Years | L53: Returns Inception
B54: Aditya Birla Sun Life Pension Fund Management Limited | C54: 42864 | D54: 52.604113 | E54: 24568 | F54: 29.3739 | G54: -0.0077089125 | H54: 0.15803446 | I54: 0.18764957 | J54: 0.13481152 | K54: NA | L54: 0.13739236
B55: Axis Pension Fund Management Limited | C55: 44855 | D55: 20.527381 | E55: 17461 | F55: 15.1866 | G55: -0.0096320015 | H55: NA | I55: NA | J55: NA | K55: NA | L55: 0.15411519
B56: HDFC Pension Fund Management Ltd. | C56: 41487 | D56: 1717.3317 | E56: 376461 | F56: 47.4362 | G56: 0.0012432114 | H56: 0.15750511 | I56: 0.19365051 | J56: 0.14202694 | K56: 0.14165622 | L56: 0.13679405
B57: ICICI Pru. Pension Fund Mgmt Co. Ltd. | C57: 40168 | D57: 700.8028 | E57: 147149 | F57: 58.6057 | G57: 0.0012659828 | H57: 0.16533794 | I57: 0.20158898 | J57: 0.14317402 | K57: 0.13814838 | L57: 0.11876536
B58: Kotak Mahindra Pension Fund Ltd. | C58: 40161 | D58: 187.89954 | E58: 34786 | F58: 61.4967 | G58: 0.020463465 | H58: 0.17170555 | I58: 0.20255317 | J58: 0.14732186 | K58: 0.14044321 | L58: 0.12203232
B59: LIC Pension Fund Ltd. | C59: 41498 | D59: 184.19515 | E59: 91326 | F59: 38.3494 | G59: 0.0048658804 | H59: 0.14959671 | I59: 0.19818108 | J59: 0.13483745 | K59: 0.12714621 | L59: 0.11736587
B60: SBI Pension Funds Pvt. Ltd | C60: 40161 | D60: 645.49935 | E60: 346917 | F60: 53.9435 | G60: -0.032691611 | H60: 0.14523923 | I60: 0.18302884 | J60: 0.1291294 | K60: 0.12974168 | L60: 0.11275017
B61: Tata Pension Fund Management Pvt. Ltd. | C61: 44792 | D61: 75.773439 | E61: 27802 | F61: 16.1468 | G61: -0.00066223116 | H61: 0.17162875 | I61: NA | J61: NA | K61: NA | L61: 0.16786512
B62: UTI Pension Fund Ltd. | C62: 40161 | D62: 143.2233 | E62: 43510 | F62: 59.1907 | G62: 0.00026531474 | H62: 0.16438462 | I62: 0.19974304 | J62: 0.13898136 | K62: 0.13738454 | L62: 0.11931726
B63: DSP Pension Fund Managers Private Limited | C63: 45287 | D63: 79.964058 | E63: 11777 | F63: 13.0534 | G63: 0.052430441 | H63: NA | I63: NA | J63: NA | K63: NA | L63: 0.1663639
B64: Benchmark Return as on 19-09-2025 | G64: -0.0052048016 | H64: 0.15503854 | I64: 0.19906204 | J64: 0.14436863 | K64: 0.14053007 | L64: =AVERAGE(L54:L63) -> 0.13527616
G65: =AVERAGE(G54:G63) -> 0.0029839539 | H65: =AVERAGE(H54,H56,H57,H58,H59,H60,H61,H62) -> 0.16042905 | I65: =AVERAGE(I54,I56,I57,I58,I59,I60,I62) -> 0.19519931 | J65: =AVERAGE(J54,J56,J57,J58,J59,J60,J62) -> 0.13861179 | K65: =AVERAGE(K56:K60,K62) -> 0.13575337 | L65: =AVERAGE(L54:L63) -> 0.13527616
A66: SCHEME - C Tier-II | B66: Pension Fund | C66: Inception Date | D66: AUM (Rs Crs) | E66: Subscribers | F66: NAV | G66: Returns 1 Year | H66: Returns 3 Years | I66: Returns 5 Years | J66: Returns 7 Years | K66: Returns 10 Years | L66: Returns Inception
B67: Aditya Birla Sun Life Pension Fund Management Limited | C67: 42864 | D67: 21.440742 | E67: 24075 | F67: 18.8301 | G67: 0.074440102 | H67: 0.079457232 | I67: 0.0684874 | J67: 0.085092115 | K67: NA | L67: 0.078545239
B68: Axis Pension Fund Management Limited | C68: 44855 | D68: 6.0483199 | E68: 16615 | F68: 12.3453 | G68: 0.081583305 | H68: NA | I68: NA | J68: NA | K68: NA | L68: 0.0749523
B69: HDFC Pension Fund Management Ltd. | C69: 41487 | D69: 597.93189 | E69: 360755 | F69: 27.2981 | G69: 0.08345141 | H69: 0.082029573 | I69: 0.070253816 | J69: 0.087944636 | K69: 0.084995969 | L69: 0.08622127
B70: ICICI Pru. Pension Fund Mgmt Co. Ltd. | C70: 40168 | D70: 259.13849 | E70: 140631 | F70: 40.816 | G70: 0.085090375 | H70: 0.081619869 | I70: 0.069082746 | J70: 0.085123973 | K70: 0.083081792 | L70: 0.093371406
B71: Kotak Mahindra Pension Fund Ltd. | C71: 40161 | D71: 56.558783 | E71: 32906 | F71: 36.683 | G71: 0.081042053 | H71: 0.078543277 | I71: 0.065432655 | J71: 0.082654583 | K71: 0.080432068 | L71: 0.085879074
B72: LIC Pension Fund Ltd. | C72: 41498 | D72: 99.575984 | E72: 91262 | F72: 26.9877 | G72: 0.083390873 | H72: 0.07953001 | I72: 0.074210473 | J72: 0.089240553 | K72: 0.083775638 | L72: 0.085418634
B73: SBI Pension Funds Pvt. Ltd | C73: 40161 | D73: 301.56229 | E73: 343487 | F73: 39.5126 | G73: 0.08310673 | H73: 0.08013404 | I73: 0.065953016 | J73: 0.082880085 | K73: 0.080604223 | L73: 0.091005926
B74: Tata Pension Fund Management Pvt. Ltd. | C74: 44792 | D74: 23.193449 | E74: 25339 | F74: 12.6507 | G74: 0.082422096 | H74: 0.080356328 | I74: NA | J74: NA | K74: NA | L74: 0.079124882
B75: UTI Pension Fund Ltd. | C75: 40161 | D75: 46.392796 | E75: 41261 | F75: 37.3666 | G75: 0.084255823 | H75: 0.080193181 | I75: 0.066407162 | J75: 0.083595859 | K75: 0.080396195 | L75: 0.087150756
B76: DSP Pension Fund Managers Private Limited | C76: 45287 | D76: 13.71333 | E76: 9422 | F76: 11.7668 | G76: 0.092117353 | H76: NA | I76: NA | J76: NA | K76: NA | L76: 0.098518678
B77: Benchmark Return as on 19-09-2025 | G77: 0.078317222 | H77: 0.077718333 | I77: 0.070755054 | J77: 0.089466249 | K77: 0.084478648
A79: SCHEME - G Tier-II | B79: Pension Fund | C79: Inception Date | D79: AUM (Rs Crs) | E79: Subscribers | F79: NAV | G79: Returns 1 Year | H79: Returns 3 Years | I79: Returns 5 Years | J79: Returns 7 Years | K79: Returns 10 Years | L79: Returns Inception
B80: Aditya Birla Sun Life Pension Fund Management Limited | C80: 42864 | D80: 39.402157 | E80: 23919 | F80: 18.1337 | G80: 0.054861378 | H80: 0.081950577 | I80: 0.064390155 | J80: 0.088923576 | K80: NA | L80: 0.0737001
B81: Axis Pension Fund Management Limited | C81: 44855 | D81: 8.6194662 | E81: 16561 | F81: 12.4077 | G81: 0.052454344 | H81: NA | I81: NA | J81: NA | K81: NA | L81: 0.076813117
B82: HDFC Pension Fund Management Ltd. | C82: 41487 | D82: 893.76974 | E82: 356739 | F82: 28.3999 | G82: 0.050070806 | H82: 0.08069001 | I82: 0.061975527 | J82: 0.08813866 | K82: 0.081597861 | L82: 0.089766702
B83: ICICI Pru. Pension Fund Mgmt Co. Ltd. | C83: 40177 | D83: 399.62938 | E83: 137955 | F83: 36.0014 | G83: 0.055245833 | H83: 0.081062371 | I83: 0.063251516 | J83: 0.087657735 | K83: 0.081897131 | L83: 0.084834251
B84: Kotak Mahindra Pension Fund Ltd. | C84: 40161 | D84: 96.300559 | E84: 32585 | F84: 34.3122 | G84: 0.042271405 | H84: 0.076446144 | I84: 0.06073137 | J84: 0.084995729 | K84: 0.08012435 | L84: 0.081289834
B85: LIC Pension Fund Ltd. | C85: 41498 | D85: 312.19901 | E85: 96290 | F85: 30.9835 | G85: 0.059478664 | H85: 0.083144642 | I85: 0.065234334 | J85: 0.095567728 | K85: 0.089338154 | L85: 0.097862576
B86: SBI Pension Funds Pvt. Ltd | C86: 40161 | D86: 634.63542 | E86: 345844 | F86: 38.7817 | G86: 0.059010341 | H86: 0.084609663 | I86: 0.064040313 | J86: 0.088323068 | K86: 0.082568208 | L86: 0.089715415
B87: Tata Pension Fund Management Pvt. Ltd. | C87: 44792 | D87: 25.443067 | E87: 25267 | F87: 12.6857 | G87: 0.048127768 | H87: 0.081358917 | I87: NA | J87: NA | K87: NA | L87: 0.080090907
B88: UTI Pension Fund Ltd. | C88: 40161 | D88: 91.899854 | E88: 41307 | F88: 37.3489 | G88: 0.059308862 | H88: 0.082039805 | I88: 0.063017458 | J88: 0.087820489 | K88: 0.080933782 | L88: 0.087118105
B89: DSP Pension Fund Managers Private Limited | C89: 45287 | D89: 18.025823 | E89: 9249 | F89: 11.5014 | G89: 0.072931826 | H89: NA | I89: NA | J89: NA | K89: NA | L89: 0.08414022
B90: Benchmark Return as on 19-09-2025 | G90: 0.059792288 | H90: 0.08364877 | I90: 0.061594142 | J90: 0.086560489 | K90: 0.079223655
A92: SCHEME -CG | B92: Pension Fund | C92: Inception Date | D92: AUM (Rs Crs) | E92: Subscribers | F92: NAV | G92: Returns 1 Year | H92: Returns 3 Years | I92: Returns 5 Years | J92: Returns 7 Years | K92: Returns 10 Years | L92: Returns Inception
B93: LIC Pension Fund Ltd. | C93: 39539 | D93: 115996.87 | E93: 2313408 | F93: 48.1545 | G93: 0.060139401 | H93: 0.092879174 | I93: 0.084828851 | J93: 0.09490573 | K93: 0.089851041 | L93: 0.094091584
B94: SBI Pension Funds Pvt. Ltd | C94: 39539 | D94: 121204.91 | E94: 2313408 | F94: 49.2895 | G94: 0.060461324 | H94: 0.091607898 | I94: 0.081834155 | J94: 0.094191455 | K94: 0.089480549 | L94: 0.095550753
B95: UTI Pension Fund Ltd. | C95: 39539 | D95: 114924.32 | E95: 2313408 | F95: 47.9544 | G95: 0.06063535 | H95: 0.093252312 | I95: 0.084351727 | J95: 0.09461209 | K95: 0.090337191 | L95: 0.093830975
B96: Benchmark Return as on 19-09-2025 | G96: 0.057241242 | H96: 0.092191717 | I96: 0.084477001 | J96: 0.097169363 | K96: 0.090268916
A98: SCHEME - SG | B98: Pension Fund | C98: Inception Date | D98: AUM (Rs Crs) | E98: Subscribers | F98: NAV | G98: Returns 1 Year | H98: Returns 3 Years | I98: Returns 5 Years | J98: Returns 7 Years | K98: Returns 10 Years | L98: Returns Inception
B99: LIC Pension Fund Ltd. | C99: 39989 | D99: 251446.84 | E99: 7002430 | F99: 42.8434 | G99: 0.05996858 | H99: 0.092726985 | I99: 0.084261294 | J99: 0.094525082 | K99: 0.08921003 | L99: 0.093687785
B100: SBI Pension Funds Pvt. Ltd | C100: 39989 | D100: 255080.89 | E100: 7002417 | F100: 42.2541 | G100: 0.057499887 | H100: 0.091252494 | I100: 0.081008031 | J100: 0.094022166 | K100: 0.089239491 | L100: 0.092755812
B101: UTI Pension Fund Ltd. | C101: 39989 | D101: 244541.56 | E101: 7002418 | F101: 42.6876 | G101: 0.060482449 | H101: 0.093384554 | I101: 0.084244033 | J101: 0.09463616 | K101: 0.09001453 | L101: 0.093442564
B102: Benchmark Return as on 19-09-2025 | G102: 0.057241242 | H102: 0.092191717 | I102: 0.084477001 | J102: 0.097169363 | K102: 0.090268916
A104: SCHEME-Corporate CG | B104: Pension Fund | C104: Inception Date | D104: AUM (Rs Crs) | E104: Subscribers | F104: NAV | G104: Returns 1 Year | H104: Returns 3 Years | I104: Returns 5 Years | J104: Returns 7 Years | K104: Returns 10 Years | L104: Returns Inception
B105: LIC Pension Fund Ltd. | C105: 41218 | D105: 4792.6807 | E105: 32051 | F105: 31.7253 | G105: 0.057414833 | H105: 0.091720695 | I105: 0.085056222 | J105: 0.095744218 | K105: 0.090070052 | L105: 0.093780902
B106: SBI Pension Funds Pvt. Ltd | C106: 41214 | D106: 91560.43 | E106: 565625 | F106: 31.3534 | G106: 0.054899282 | H106: 0.090886528 | I106: 0.080749583 | J106: 0.093918636 | K106: 0.089496896 | L106: 0.092698373
B107: Benchmark Return as on 19-09-2025 | G107: 0.057241242 | H107: 0.092191717 | I107: 0.084477001 | J107: 0.097169363 | K107: 0.090268916
A109: SCHEME- NPS Lite | B109: Pension Fund | C109: Inception Date | D109: AUM (Rs Crs) | E109: Subscribers | F109: NAV | G109: Returns 1 Year | H109: Returns 3 Years | I109: Returns 5 Years | J109: Returns 7 Years | K109: Returns 10 Years | L109: Returns Inception
...

Sheet NPS Funds Returns
C3: Returns 1 Year | D3: Returns 3 Years | E3: Returns 5 Years | F3: Returns 7 Years | G3: Returns 10 Years | H3: Returns Inception
B4: Equity Tier1 | C4: ='Funds & Performance'!G14 -> -0.00026921239 | D4: ='Funds & Performance'!H14 -> 0.16048337 | E4: ='Funds & Performance'!I14 -> 0.1950024 | F4: ='Funds & Performance'!J14 -> 0.13844497 | G4: ='Funds & Performance'!K14 -> 0.13625084 | H4: ='Funds & Performance'!L14 -> 0.14129474 | J4: TO SUPPORT OUR CHANNEL USE THE LINKS BELOW
B5: Equity Tier2 | C5: ='Funds & Performance'!G65 -> 0.0029839539 | D5: ='Funds & Performance'!H65 -> 0.16042905 | E5: ='Funds & Performance'!I65 -> 0.19519931 | F5: ='Funds & Performance'!J65 -> 0.13861179 | G5: ='Funds & Performance'!K65 -> 0.13575337 | H5: ='Funds & Performance'!L65 -> 0.13527616 | J5: https://angel-one.onelink.me/Wjgr/8vxyj8iq | K5: LINK FOR ANGEL ONE
B6: No. of Funds | C6: 10 | D6: 8 | E6: 7 | F6: 7 | G6: 6 | H6: 10 | J6: https://tinyurl.com/y8sbw9w8 | K6: LINK FOR UPSTOX
B7: Benchmark | C7: ='Funds & Performance'!G64 -> -0.0052048016 | D7: ='Funds & Performance'!H64 -> 0.15503854 | E7: ='Funds & Performance'!I64 -> 0.19906204 | F7: ='Funds & Performance'!J64 -> 0.14436863 | G7: ='Funds & Performance'!K64 -> 0.14053007 | J7: https://zerodha.com/open-account?c=ZMPVNW | K7: LINK FOR ZERODHA

Sheet New NPS Vs Old NPS
I4: Calculation of Investment in Old NPS | O4: Calculation of Investment in New NPS
C5: Name | D5: abc | I5: Expected Growth in Salary | L5: =D14 -> 0.07 | O5: Expected Growth in Salary | R5: =D14 -> 0.07
C6: Age | D6: 25 | I6: Expected Return on Investment | L6: 0.1 | O6: Expected Return on Investment | R6: =D15 -> 0.12
C7: Planned Vesting Age | D7: 60 | I7: Year | J7: Investment | K7: Contribution | L7: End Value | O7: Year | P7: Investment | Q7: Contribution | R7: End Value
C8: Planned Investment Amount | D8: 10000 | I8: 1 | J8: 0 | K8: =D11*12 -> 120000 | L8: =FV(NOMINAL($L$6,12)/12,12,-K8/12,-J8) -> 125405.37 | O8: 1 | P8: 0 | Q8: =K8 -> 120000 | R8: =FV(NOMINAL($R$6,12)/12,12,-Q8/12,-P8) -> 126464.98
I9: =IF(I8>=($D$7-$D$6), "NA",I8+1) -> 2 | J9: =IF(I9= "NA",0,L8) -> 125405.37 | K9: =IF(I9="NA",0,IF(K8*(1+$L$5)<750000,K8*(1+$L$5),750000)) -> 128400 | L9: =FV(NOMINAL($L$6,12)/12,12,-K9/12,-J9) -> 272129.64 | O9: =IF(O8>=($D$7-$D$6), "NA",O8+1) -> 2 | P9: =IF(O9= "NA",0,R8) -> 126464.98 | Q9: =K9 -> 128400 | R9: =FV(NOMINAL($R$6,12)/12,12,-Q9/12,-P9) -> 276958.3
I10: =IF(I9>=($D$7-$D$6), "NA",I9+1) -> 3 | J10: =IF(I10= "NA",0,L9) -> 272129.64 | K10: =IF(I10="NA",0,IF(K9*(1+$L$5)<750000,K9*(1+$L$5),750000)) -> 137388 | L10: =FV(NOMINAL($L$6,12)/12,12,-K10/12,-J10) -> 442919.21 | O10: =IF(O9>=($D$7-$D$6), "NA",O9+1) -> 3 | P10: =IF(O10= "NA",0,R9) -> 276958.3 | Q10: =K10 -> 137388 | R10: =FV(NOMINAL($R$6,12)/12,12,-Q10/12,-P10) -> 454983.06
C11: Contribution to Old NPS | D11: =D8 -> 10000 | I11: =IF(I10>=($D$7-$D$6), "NA",I10+1) -> 4 | J11: =IF(I11= "NA",0,L10) -> 442919.21 | K11: =IF(I11="NA",0,IF(K10*(1+$L$5)<750000,K10*(1+$L$5),750000)) -> 147005.16 | L11: =FV(NOMINAL($L$6,12)/12,12,-K11/12,-J11) -> 640838.1 | O11: =IF(O10>=($D$7-$D$6), "NA",O10+1) -> 4 | P11: =IF(O11= "NA",0,R10) -> 454983.06 | Q11: =K11 -> 147005.16 | R11: =FV(NOMINAL($R$6,12)/12,12,-Q11/12,-P11) -> 664506.06
C12: Contribution to New NPS | D12: =D8*(1-D9) -> 10000 | I12: =IF(I11>=($D$7-$D$6), "NA",I11+1) -> 5 | J12: =IF(I12= "NA",0,L11) -> 640838.1 | K12: =IF(I12="NA",0,IF(K11*(1+$L$5)<750000,K11*(1+$L$5),750000)) -> 157295.52 | L12: =FV(NOMINAL($L$6,12)/12,12,-K12/12,-J12) -> 869302.76 | O12: =IF(O11>=($D$7-$D$6), "NA",O11+1) -> 5 | P12: =IF(O12= "NA",0,R11) -> 664506.06 | Q12: =K12 -> 157295.52 | R12: =FV(NOMINAL($R$6,12)/12,12,-Q12/12,-P12) -> 910016.58
I13: =IF(I12>=($D$7-$D$6), "NA",I12+1) -> 6 | J13: =IF(I13= "NA",0,L12) -> 869302.76 | K13: =IF(I13="NA",0,IF(K12*(1+$L$5)<750000,K12*(1+$L$5),750000)) -> 168306.21 | L13: =FV(NOMINAL($L$6,12)/12,12,-K13/12,-J13) -> 1132120.6 | O13: =IF(O12>=($D$7-$D$6), "NA",O12+1) -> 6 | P13: =IF(O13= "NA",0,R12) -> 910016.58 | Q13: =K13 -> 168306.21 | R13: =FV(NOMINAL($R$6,12)/12,12,-Q13/12,-P13) -> 1196592.2
C14: Expected Growth in Salary | D14: 0.07 | I14: =IF(I13>=($D$7-$D$6), "NA",I13+1) -> 7 | J14: =IF(I14= "NA",0,L13) -> 1132120.6 | K14: =IF(I14="NA",0,IF(K13*(1+$L$5)<750000,K13*(1+$L$5),750000)) -> 180087.64 | L14: =FV(NOMINAL($L$6,12)/12,12,-K14/12,-J14) -> 1433532.2 | O14: =IF(O13>=($D$7-$D$6), "NA",O13+1) -> 7 | P14: =IF(O14= "NA",0,R13) -> 1196592.2 | Q14: =K14 -> 180087.64 | R14: =FV(NOMINAL($R$6,12)/12,12,-Q14/12,-P14) -> 1529973.1
C15: Expected Return on Investment | D15: 0.12 | I15: =IF(I14>=($D$7-$D$6), "NA",I14+1) -> 8 | J15: =IF(I15= "NA",0,L14) -> 1433532.2 | K15: =IF(I15="NA",0,IF(K14*(1+$L$5)<750000,K14*(1+$L$5),750000)) -> 192693.78 | L15: =FV(NOMINAL($L$6,12)/12,12,-K15/12,-J15) -> 1778259.1 | O15: =IF(O14>=($D$7-$D$6), "NA",O14+1) -> 8 | P15: =IF(O15= "NA",0,R14) -> 1529973.1 | Q15: =K15 -> 192693.78 | R15: =FV(NOMINAL($R$6,12)/12,12,-Q15/12,-P15) -> 1916645
I16: =IF(I15>=($D$7-$D$6), "NA",I15+1) -> 9 | J16: =IF(I16= "NA",0,L15) -> 1778259.1 | K16: =IF(I16="NA",0,IF(K15*(1+$L$5)<750000,K15*(1+$L$5),750000)) -> 206182.34 | L16: =FV(NOMINAL($L$6,12)/12,12,-K16/12,-J16) -> 2171554.8 | O16: =IF(O15>=($D$7-$D$6), "NA",O15+1) -> 9 | P16: =IF(O16= "NA",0,R15) -> 1916645 | Q16: =K16 -> 206182.34 | R16: =FV(NOMINAL($R$6,12)/12,12,-Q16/12,-P16) -> 2363932.8
I17: =IF(I16>=($D$7-$D$6), "NA",I16+1) -> 10 | J17: =IF(I17= "NA",0,L16) -> 2171554.8 | K17: =IF(I17="NA",0,IF(K16*(1+$L$5)<750000,K16*(1+$L$5),750000)) -> 220615.11 | L17: =FV(NOMINAL($L$6,12)/12,12,-K17/12,-J17) -> 2619262.9 | O17: =IF(O16>=($D$7-$D$6), "NA",O16+1) -> 10 | P17: =IF(O17= "NA",0,R16) -> 2363932.8 | Q17: =K17 -> 220615.11 | R17: =FV(NOMINAL($R$6,12)/12,12,-Q17/12,-P17) -> 2880105.5
C18: TO SUPPORT OUR CHANNEL USE THE LINKS BELOW | I18: =IF(I17>=($D$7-$D$6), "NA",I17+1) -> 11 | J18: =IF(I18= "NA",0,L17) -> 2619262.9 | K18: =IF(I18="NA",0,IF(K17*(1+$L$5)<750000,K17*(1+$L$5),750000)) -> 236058.16 | L18: =FV(NOMINAL($L$6,12)/12,12,-K18/12,-J18) -> 3127880.5 | O18: =IF(O17>=($D$7-$D$6), "NA",O17+1) -> 11 | P18: =IF(O18= "NA",0,R17) -> 2880105.5 | Q18: =K18 -> 236058.16 | R18: =FV(NOMINAL($R$6,12)/12,12,-Q18/12,-P18) -> 3474493.9
C19: https://angel-one.onelink.me/Wjgr/8vxyj8iq | D19: LINK FOR ANGEL ONE | I19: =IF(I18>=($D$7-$D$6), "NA",I18+1) -> 12 | J19: =IF(I19= "NA",0,L18) -> 3127880.5 | K19: =IF(I19="NA",0,IF(K18*(1+$L$5)<750000,K18*(1+$L$5),750000)) -> 252582.23 | L19: =FV(NOMINAL($L$6,12)/12,12,-K19/12,-J19) -> 3704628.3 | O19: =IF(O18>=($D$7-$D$6), "NA",O18+1) -> 12 | P19: =IF(O19= "NA",0,R18) -> 3474493.9 | Q19: =K19 -> 252582.23 | R19: =FV(NOMINAL($R$6,12)/12,12,-Q19/12,-P19) -> 4157623.2
C20: https://tinyurl.com/y8sbw9w8 | D20: LINK FOR UPSTOX | I20: =IF(I19>=($D$7-$D$6), "NA",I19+1) -> 13 | J20: =IF(I20= "NA",0,L19) -> 3704628.3 | K20: =IF(I20="NA",0,IF(K19*(1+$L$5)<750000,K19*(1+$L$5),750000)) -> 270262.99 | L20: =FV(NOMINAL($L$6,12)/12,12,-K20/12,-J20) -> 4357528 | O20: =IF(O19>=($D$7-$D$6), "NA",O19+1) -> 13 | P20: =IF(O20= "NA",0,R19) -> 4157623.2 | Q20: =K20 -> 270262.99 | R20: =FV(NOMINAL($R$6,12)/12,12,-Q20/12,-P20) -> 4941361.4
C21: https://zerodha.com/open-account?c=ZMPVNW | D21: LINK FOR ZERODHA | I21: =IF(I20>=($D$7-$D$6), "NA",I20+1) -> 14 | J21: =IF(I21= "NA",0,L20) -> 4357528 | K21: =IF(I21="NA",0,IF(K20*(1+$L$5)<750000,K20*(1+$L$5),750000)) -> 289181.4 | L21: =FV(NOMINAL($L$6,12)/12,12,-K21/12,-J21) -> 5095488.3 | O21: =IF(O20>=($D$7-$D$6), "NA",O20+1) -> 14 | P21: =IF(O21= "NA",0,R20) -> 4941361.4 | Q21: =K21 -> 289181.4 | R21: =FV(NOMINAL($R$6,12)/12,12,-Q21/12,-P21) -> 5839085.7
I22: =IF(I21>=($D$7-$D$6), "NA",I21+1) -> 15 | J22: =IF(I22= "NA",0,L21) -> 5095488.3 | K22: =IF(I22="NA",0,IF(K21*(1+$L$5)<750000,K21*(1+$L$5),750000)) -> 309424.1 | L22: =FV(NOMINAL($L$6,12)/12,12,-K22/12,-J22) -> 5928399.2 | O22: =IF(O21>=($D$7-$D$6), "NA",O21+1) -> 15 | P22: =IF(O22= "NA",0,R21) -> 5839085.7 | Q22: =K22 -> 309424.1 | R22: =FV(NOMINAL($R$6,12)/12,12,-Q22/12,-P22) -> 6865870.3
I23: =IF(I22>=($D$7-$D$6), "NA",I22+1) -> 16 | J23: =IF(I23= "NA",0,L22) -> 5928399.2 | K23: =IF(I23="NA",0,IF(K22*(1+$L$5)<750000,K22*(1+$L$5),750000)) -> 331083.78 | L23: =FV(NOMINAL($L$6,12)/12,12,-K23/12,-J23) -> 6867236.5 | O23: =IF(O22>=($D$7-$D$6), "NA",O22+1) -> 16 | P23: =IF(O23= "NA",0,R22) -> 6865870.3 | Q23: =K23 -> 331083.78 | R23: =FV(NOMINAL($R$6,12)/12,12,-Q23/12,-P23) -> 8038695.6
I24: =IF(I23>=($D$7-$D$6), "NA",I23+1) -> 17 | J24: =IF(I24= "NA",0,L23) -> 6867236.5 | K24: =IF(I24="NA",0,IF(K23*(1+$L$5)<750000,K23*(1+$L$5),750000)) -> 354259.65 | L24: =FV(NOMINAL($L$6,12)/12,12,-K24/12,-J24) -> 7924177.3 | O24: =IF(O23>=($D$7-$D$6), "NA",O23+1) -> 17 | P24: =IF(O24= "NA",0,R23) -> 8038695.6 | Q24: =K24 -> 354259.65 | R24: =FV(NOMINAL($R$6,12)/12,12,-Q24/12,-P24) -> 9376684.4
C25: The Difference in Gains | I25: =IF(I24>=($D$7-$D$6), "NA",I24+1) -> 18 | J25: =IF(I25= "NA",0,L24) -> 7924177.3 | K25: =IF(I25="NA",0,IF(K24*(1+$L$5)<750000,K24*(1+$L$5),750000)) -> 379057.83 | L25: =FV(NOMINAL($L$6,12)/12,12,-K25/12,-J25) -> 9112727.4 | O25: =IF(O24>=($D$7-$D$6), "NA",O24+1) -> 18 | P25: =IF(O25= "NA",0,R24) -> 9376684.4 | Q25: =K25 -> 379057.83 | R25: =FV(NOMINAL($R$6,12)/12,12,-Q25/12,-P25) -> 10901366
C26: End Corpus from Old NPS | D26: =MAX(L8:L42) -> 70747757 | I26: =IF(I25>=($D$7-$D$6), "NA",I25+1) -> 19 | J26: =IF(I26= "NA",0,L25) -> 9112727.4 | K26: =IF(I26="NA",0,IF(K25*(1+$L$5)<750000,K25*(1+$L$5),750000)) -> 405591.87 | L26: =FV(NOMINAL($L$6,12)/12,12,-K26/12,-J26) -> 10447862 | O26: =IF(O25>=($D$7-$D$6), "NA",O25+1) -> 19 | P26: =IF(O26= "NA",0,R25) -> 10901366 | Q26: =K26 -> 405591.87 | R26: =FV(NOMINAL($R$6,12)/12,12,-Q26/12,-P26) -> 12636973
C27: End Corpus from New NPS | D27: =MAX(R7:R42) -> 1.0434366e+08 | I27: =IF(I26>=($D$7-$D$6), "NA",I26+1) -> 20 | J27: =IF(I27= "NA",0,L26) -> 10447862 | K27: =IF(I27="NA",0,IF(K26*(1+$L$5)<750000,K26*(1+$L$5),750000)) -> 433983.3 | L27: =FV(NOMINAL($L$6,12)/12,12,-K27/12,-J27) -> 11946180 | O27: =IF(O26>=($D$7-$D$6), "NA",O26+1) -> 20 | P27: =IF(O27= "NA",0,R26) -> 12636973 | Q27: =K27 -> 433983.3 | R27: =FV(NOMINAL($R$6,12)/12,12,-Q27/12,-P27) -> 14610774
C28: The Additional Corpus from New NPS | D28: =D27-D26 -> 33595898 | I28: =IF(I27>=($D$7-$D$6), "NA",I27+1) -> 21 | J28: =IF(I28= "NA",0,L27) -> 11946180 | K28: =IF(I28="NA",0,IF(K27*(1+$L$5)<750000,K27*(1+$L$5),750000)) -> 464362.14 | L28: =FV(NOMINAL($L$6,12)/12,12,-K28/12,-J28) -> 13626077 | O28: =IF(O27>=($D$7-$D$6), "NA",O27+1) -> 21 | P28: =IF(O28= "NA",0,R27) -> 14610774 | Q28: =K28 -> 464362.14 | R28: =FV(NOMINAL($R$6,12)/12,12,-Q28/12,-P28) -> 16853446
C29: Rate of Additional Return | D29: =D28/D26 -> 0.47486875 | I29: =IF(I28>=($D$7-$D$6), "NA",I28+1) -> 22 | J29: =IF(I29= "NA",0,L28) -> 13626077 | K29: =IF(I29="NA",0,IF(K28*(1+$L$5)<750000,K28*(1+$L$5),750000)) -> 496867.48 | L29: =FV(NOMINAL($L$6,12)/12,12,-K29/12,-J29) -> 15507934 | O29: =IF(O28>=($D$7-$D$6), "NA",O28+1) -> 22 | P29: =IF(O29= "NA",0,R28) -> 16853446 | Q29: =K29 -> 496867.48 | R29: =FV(NOMINAL($R$6,12)/12,12,-Q29/12,-P29) -> 19399496
I30: =IF(I29>=($D$7-$D$6), "NA",I29+1) -> 23 | J30: =IF(I30= "NA",0,L29) -> 15507934 | K30: =IF(I30="NA",0,IF(K29*(1+$L$5)<750000,K29*(1+$L$5),750000)) -> 531648.21 | L30: =FV(NOMINAL($L$6,12)/12,12,-K30/12,-J30) -> 17614323 | O30: =IF(O29>=($D$7-$D$6), "NA",O29+1) -> 23 | P30: =IF(O30= "NA",0,R29) -> 19399496 | Q30: =K30 -> 531648.21 | R30: =FV(NOMINAL($R$6,12)/12,12,-Q30/12,-P30) -> 22287726
I31: =IF(I30>=($D$7-$D$6), "NA",I30+1) -> 24 | J31: =IF(I31= "NA",0,L30) -> 17614323 | K31: =IF(I31="NA",0,IF(K30*(1+$L$5)<750000,K30*(1+$L$5),750000)) -> 568863.58 | L31: =FV(NOMINAL($L$6,12)/12,12,-K31/12,-J31) -> 19970243 | O31: =IF(O30>=($D$7-$D$6), "NA",O30+1) -> 24 | P31: =IF(O31= "NA",0,R30) -> 22287726 | Q31: =K31 -> 568863.58 | R31: =FV(NOMINAL($R$6,12)/12,12,-Q31/12,-P31) -> 25561764
I32: =IF(I31>=($D$7-$D$6), "NA",I31+1) -> 25 | J32: =IF(I32= "NA",0,L31) -> 19970243 | K32: =IF(I32="NA",0,IF(K31*(1+$L$5)<750000,K31*(1+$L$5),750000)) -> 608684.03 | L32: =FV(NOMINAL($L$6,12)/12,12,-K32/12,-J32) -> 22603370 | O32: =IF(O31>=($D$7-$D$6), "NA",O31+1) -> 25 | P32: =IF(O32= "NA",0,R31) -> 25561764 | Q32: =K32 -> 608684.03 | R32: =FV(NOMINAL($R$6,12)/12,12,-Q32/12,-P32) -> 29270653
I33: =IF(I32>=($D$7-$D$6), "NA",I32+1) -> 26 | J33: =IF(I33= "NA",0,L32) -> 22603370 | K33: =IF(I33="NA",0,IF(K32*(1+$L$5)<750000,K32*(1+$L$5),750000)) -> 651291.92 | L33: =FV(NOMINAL($L$6,12)/12,12,-K33/12,-J33) -> 25544336 | O33: =IF(O32>=($D$7-$D$6), "NA",O32+1) -> 26 | P33: =IF(O33= "NA",0,R32) -> 29270653 | Q33: =K33 -> 651291.92 | R33: =FV(NOMINAL($R$6,12)/12,12,-Q33/12,-P33) -> 33469511
I34: =IF(I33>=($D$7-$D$6), "NA",I33+1) -> 27 | J34: =IF(I34= "NA",0,L33) -> 25544336 | K34: =IF(I34="NA",0,IF(K33*(1+$L$5)<750000,K33*(1+$L$5),750000)) -> 696882.35 | L34: =FV(NOMINAL($L$6,12)/12,12,-K34/12,-J34) -> 28827043 | O34: =IF(O33>=($D$7-$D$6), "NA",O33+1) -> 27 | P34: =IF(O34= "NA",0,R33) -> 33469511 | Q34: =K34 -> 696882.35 | R34: =FV(NOMINAL($R$6,12)/12,12,-Q34/12,-P34) -> 38220279
I35: =IF(I34>=($D$7-$D$6), "NA",I34+1) -> 28 | J35: =IF(I35= "NA",0,L34) -> 28827043 | K35: =IF(I35="NA",0,IF(K34*(1+$L$5)<750000,K34*(1+$L$5),750000)) -> 745664.12 | L35: =FV(NOMINAL($L$6,12)/12,12,-K35/12,-J35) -> 32488999 | O35: =IF(O34>=($D$7-$D$6), "NA",O34+1) -> 28 | P35: =IF(O35= "NA",0,R34) -> 38220279 | Q35: =K35 -> 745664.12 | R35: =FV(NOMINAL($R$6,12)/12,12,-Q35/12,-P35) -> 43592549
I36: =IF(I35>=($D$7-$D$6), "NA",I35+1) -> 29 | J36: =IF(I36= "NA",0,L35) -> 32488999 | K36: =IF(I36="NA",0,IF(K35*(1+$L$5)<750000,K35*(1+$L$5),750000)) -> 750000 | L36: =FV(NOMINAL($L$6,12)/12,12,-K36/12,-J36) -> 36521683 | O36: =IF(O35>=($D$7-$D$6), "NA",O35+1) -> 29 | P36: =IF(O36= "NA",0,R35) -> 43592549 | Q36: =K36 -> 750000 | R36: =FV(NOMINAL($R$6,12)/12,12,-Q36/12,-P36) -> 49614061
I37: =IF(I36>=($D$7-$D$6), "NA",I36+1) -> 30 | J37: =IF(I37= "NA",0,L36) -> 36521683 | K37: =IF(I37="NA",0,IF(K36*(1+$L$5)<750000,K36*(1+$L$5),750000)) -> 750000 | L37: =FV(NOMINAL($L$6,12)/12,12,-K37/12,-J37) -> 40957634 | O37: =IF(O36>=($D$7-$D$6), "NA",O36+1) -> 30 | P37: =IF(O37= "NA",0,R36) -> 49614061 | Q37: =K37 -> 750000 | R37: =FV(NOMINAL($R$6,12)/12,12,-Q37/12,-P37) -> 56358155
I38: =IF(I37>=($D$7-$D$6), "NA",I37+1) -> 31 | J38: =IF(I38= "NA",0,L37) -> 40957634 | K38: =IF(I38="NA",0,IF(K37*(1+$L$5)<750000,K37*(1+$L$5),750000)) -> 750000 | L38: =FV(NOMINAL($L$6,12)/12,12,-K38/12,-J38) -> 45837181 | O38: =IF(O37>=($D$7-$D$6), "NA",O37+1) -> 31 | P38: =IF(O38= "NA",0,R37) -> 56358155 | Q38: =K38 -> 750000 | R38: =FV(NOMINAL($R$6,12)/12,12,-Q38/12,-P38) -> 63911540
I39: =IF(I38>=($D$7-$D$6), "NA",I38+1) -> 32 | J39: =IF(I39= "NA",0,L38) -> 45837181 | K39: =IF(I39="NA",0,IF(K38*(1+$L$5)<750000,K38*(1+$L$5),750000)) -> 750000 | L39: =FV(NOMINAL($L$6,12)/12,12,-K39/12,-J39) -> 51204683 | O39: =IF(O38>=($D$7-$D$6), "NA",O38+1) -> 32 | P39: =IF(O39= "NA",0,R38) -> 63911540 | Q39: =K39 -> 750000 | R39: =FV(NOMINAL($R$6,12)/12,12,-Q39/12,-P39) -> 72371331
I40: =IF(I39>=($D$7-$D$6), "NA",I39+1) -> 33 | J40: =IF(I40= "NA",0,L39) -> 51204683 | K40: =IF(I40="NA",0,IF(K39*(1+$L$5)<750000,K39*(1+$L$5),750000)) -> 750000 | L40: =FV(NOMINAL($L$6,12)/12,12,-K40/12,-J40) -> 57108935 | O40: =IF(O39>=($D$7-$D$6), "NA",O39+1) -> 33 | P40: =IF(O40= "NA",0,R39) -> 72371331 | Q40: =K40 -> 750000 | R40: =FV(NOMINAL($R$6,12)/12,12,-Q40/12,-P40) -> 81846296
I41: =IF(I40>=($D$7-$D$6), "NA",I40+1) -> 34 | J41: =IF(I41= "NA",0,L40) -> 57108935 | K41: =IF(I41="NA",0,IF(K40*(1+$L$5)<750000,K40*(1+$L$5),750000)) -> 750000 | L41: =FV(NOMINAL($L$6,12)/12,12,-K41/12,-J41) -> 63603612 | O41: =IF(O40>=($D$7-$D$6), "NA",O40+1) -> 34 | P41: =IF(O41= "NA",0,R40) -> 81846296 | Q41: =K41 -> 750000 | R41: =FV(NOMINAL($R$6,12)/12,12,-Q41/12,-P41) -> 92458258
I42: =IF(I41>=($D$7-$D$6), "NA",I41+1) -> 35 | J42: =IF(I42= "NA",0,L41) -> 63603612 | K42: =IF(I42="NA",0,IF(K41*(1+$L$5)<750000,K41*(1+$L$5),750000)) -> 750000 | L42: =FV(NOMINAL($L$6,12)/12,12,-K42/12,-J42) -> 70747757 | O42: =IF(O41>=($D$7-$D$6), "NA",O41+1) -> 35 | P42: =IF(O42= "NA",0,R41) -> 92458258 | Q42: =K42 -> 750000 | R42: =FV(NOMINAL($R$6,12)/12,12,-Q42/12,-P42) -> 1.0434366e+08
